vidis_algorithms_api/Lifecycle.py
vidis_algorithms_api/Task.py
vidis_algorithms_api/__init__.py
vidis_algorithms_api/core/Settings.py
vidis_algorithms_api/core/__init__.py
vidis_algorithms_api-0.4.8.dist-info/METADATA
vidis_algorithms_api-0.4.8.dist-info/WHEEL
vidis_algorithms_api-0.4.8.dist-info/top_level.txt
vidis_algorithms_api-0.4.8.dist-info/RECORD
