Metadata-Version: 2.4
Name: vidis_algorithms_api
Version: 0.4.8
Summary: ![Image size](https://badgen.net/badge/docker/size/banayaki/vidis-algorithms)
Home-page: https://github.com/Banayaki
Author: Artem Mukhin
License: MIT
Requires-Dist: pydantic==1.10.2
Requires-Dist: loguru==0.6.0
Requires-Dist: numpy==1.24.1
Requires-Dist: celery[amqp,redis]==5.2.7
Requires-Dist: redis==4.5.4
Requires-Dist: nameko==2.14.1
Requires-Dist: Pillow==9.5.0
Dynamic: author
Dynamic: home-page
Dynamic: license
Dynamic: requires-dist
Dynamic: summary
